dlatk_pymallet-1.0.1.dist-info/RECORD
dlatk_pymallet-1.0.1.dist-info/WHEEL
dlatk_pymallet-1.0.1.dist-info/top_level.txt
dlatk_pymallet-1.0.1.dist-info/entry_points.txt
dlatk_pymallet-1.0.1.dist-info/LICENSE
dlatk_pymallet-1.0.1.dist-info/METADATA
pymallet/lda.py
pymallet/defaults.py
pymallet/topicmodel.c
pymallet/topicmodel.cpython-38-x86_64-linux-gnu.so
pymallet/stoplists/fi.txt
pymallet/stoplists/nl.txt
pymallet/stoplists/en.txt
pymallet/stoplists/LICENSE
pymallet/stoplists/de.txt
pymallet/stoplists/README.md
pymallet/stoplists/jp.txt
pymallet/stoplists/fr.txt
