Metadata-Version: 2.1
Name: dlatk-pymallet
Version: 1.0.1
Summary: A PyMallet implementation adapted to DLATK.
Home-page: https://github.com/gtsherman/pymallet
Author: David Mimno (original PyMallet), Garrick Sherman (adaptation)
Author-email: garricks@sas.upenn.edu
License: MIT
Platform: UNKNOWN
